TensorflowRumenChuyi/README.md
TensorflowRumenChuyi/__init__.py
TensorflowRumenChuyi/__main__.py
TensorflowRumenChuyi/file.epub
TensorflowRumenChuyi/index.html
TensorflowRumenChuyi/css/__init__.py
TensorflowRumenChuyi/css/annotations.css
TensorflowRumenChuyi/css/main.css
TensorflowRumenChuyi/css/normalize.css
TensorflowRumenChuyi/css/popup.css
TensorflowRumenChuyi/font/__init__.py
TensorflowRumenChuyi/font/fontello.eot
TensorflowRumenChuyi/font/fontello.svg
TensorflowRumenChuyi/font/fontello.ttf
TensorflowRumenChuyi/font/fontello.woff
TensorflowRumenChuyi/img/__init__.py
TensorflowRumenChuyi/img/annotator-glyph-sprite.png
TensorflowRumenChuyi/img/annotator-icon-sprite.png
TensorflowRumenChuyi/img/apple-touch-icon.png
TensorflowRumenChuyi/img/cancelfullscreen.png
TensorflowRumenChuyi/img/close.png
TensorflowRumenChuyi/img/fullscreen.png
TensorflowRumenChuyi/img/loader.gif
TensorflowRumenChuyi/img/menu-icon.png
TensorflowRumenChuyi/img/save.png
TensorflowRumenChuyi/img/saved.png
TensorflowRumenChuyi/img/settings-s.png
TensorflowRumenChuyi/img/settings.png
TensorflowRumenChuyi/img/star.png
TensorflowRumenChuyi/js/__init__.py
TensorflowRumenChuyi/js/epub.js
TensorflowRumenChuyi/js/epub.min.js
TensorflowRumenChuyi/js/epub.min.map
TensorflowRumenChuyi/js/hooks.min.js
TensorflowRumenChuyi/js/hooks.min.map
TensorflowRumenChuyi/js/reader.js
TensorflowRumenChuyi/js/reader.js.map
TensorflowRumenChuyi/js/reader.min.js
TensorflowRumenChuyi/js/reader.min.map
TensorflowRumenChuyi/js/hooks/__init__.py
TensorflowRumenChuyi/js/hooks/extensions/__init__.py
TensorflowRumenChuyi/js/hooks/extensions/highlight.js
TensorflowRumenChuyi/js/libs/__init__.py
TensorflowRumenChuyi/js/libs/jquery.min.js
TensorflowRumenChuyi/js/libs/localforage.min.js
TensorflowRumenChuyi/js/libs/screenfull.js
TensorflowRumenChuyi/js/libs/screenfull.min.js
TensorflowRumenChuyi/js/libs/zip.min.js
TensorflowRumenChuyi/js/plugins/__init__.py
TensorflowRumenChuyi/js/plugins/hypothesis.js
tensorflow_rumen_chuyi-2024.3.5.0.dist-info/METADATA
tensorflow_rumen_chuyi-2024.3.5.0.dist-info/WHEEL
tensorflow_rumen_chuyi-2024.3.5.0.dist-info/entry_points.txt
tensorflow_rumen_chuyi-2024.3.5.0.dist-info/top_level.txt
tensorflow_rumen_chuyi-2024.3.5.0.dist-info/RECORD
